tests/__init__.py
tests/test_messsage.py
tests/test_websockets.py
tests/websocket_server.py
trackml/__init__.py
trackml/frameworks.py
trackml/trackml.py
trackml-0.1.12.dist-info/DESCRIPTION.rst
trackml-0.1.12.dist-info/METADATA
trackml-0.1.12.dist-info/RECORD
trackml-0.1.12.dist-info/WHEEL
trackml-0.1.12.dist-info/metadata.json
trackml-0.1.12.dist-info/top_level.txt
