Metadata-Version: 2.0
Name: trackml
Version: 0.1.12
Summary: An opinionated, minimal cookiecutter template for Python packages
Home-page: https://github.com/track-ml/python-client/
Author: Gideon
Author-email: Gideon@semantica-labs.com
License: UNKNOWN
Platform: UNKNOWN
Classifier: Development Status :: 2 - Pre-Alpha
Classifier: Programming Language :: Python
Classifier: Programming Language :: Python :: 2
Classifier: Programming Language :: Python :: 2.7
Classifier: Programming Language :: Python :: 3
Classifier: Programming Language :: Python :: 3.4
Classifier: Programming Language :: Python :: 3.5
Requires-Dist: requests (>=2.18.4)
Requires-Dist: websocket-client (>=0.44.0)
